poetry_plugin_exe/__init__.py
poetry_plugin_exe/core.py
poetry_plugin_exe-0.0.1.dist-info/entry_points.txt
poetry_plugin_exe-0.0.1.dist-info/LICENSE
poetry_plugin_exe-0.0.1.dist-info/WHEEL
poetry_plugin_exe-0.0.1.dist-info/METADATA
poetry_plugin_exe-0.0.1.dist-info/RECORD
